[
  {
    "id": "1",
    "title": "Посты Павел Бухтик",
    "link": "https://t.me/nodatanogrowth/399",
    "source": "telegram",
    "company": "independent",
    "themes": [
      "analytics-core"
    ],
    "section": "analytics",
    "summary": "Посты Павла Бухтика по продуктовой аналитике и A/B-тестированию — практические материалы от независимого эксперта.",
    "difficulty": "продвинутый"
  },
  {
    "id": "2",
    "title": "Посты Юрий Баландин",
    "link": "https://t.me/suranalytics/",
    "source": "telegram",
    "company": "independent",
    "themes": [
      "analytics-core"
    ],
    "section": "analytics",
    "summary": "Авторские посты Юрия Баландина по теме экспериментов и продуктовой аналитики.",
    "difficulty": "продвинутый"
  },
  {
    "id": "3",
    "title": "AB тестирование CUPED vs Stratification",
    "link": "https://habr.com/ru/companies/X5Tech/articles/826488/",
    "source": "habr",
    "company": "X5",
    "themes": [
      "experiments",
      "variance-reduction"
    ],
    "section": "analytics",
    "summary": "Почему t-тест не работает на малых скошенных выборках и как строить собственные критерии по историческим данным.",
    "author": "Nazarov",
    "difficulty": "продвинутый"
  },
  {
    "id": "4",
    "title": "AB тестирование множественная проверка гипотез",
    "link": "https://habr.com/ru/companies/X5Tech/articles/842426/",
    "source": "habr",
    "company": "X5",
    "themes": [
      "experiments",
      "multiple-testing"
    ],
    "section": "analytics",
    "summary": "Объясняет, почему растут ошибки первого рода при множественном тестировании и как их контролировать с помощью поправок.",
    "author": "Nazarov",
    "difficulty": "продвинутый"
  },
  {
    "id": "5",
    "title": "AB тестирование на маленьких выборках. Построение собственного критерия",
    "link": "https://habr.com/ru/companies/X5Tech/articles/801527/",
    "source": "habr",
    "company": "X5",
    "themes": [
      "experiments",
      "statistics"
    ],
    "section": "analytics",
    "summary": "Почему t-тест не работает на малых скошенных выборках и как построить собственный критерий по историческим данным.",
    "author": "Nazarov",
    "difficulty": "продвинутый"
  },
  {
    "id": "6",
    "title": "AB тестирование с CUPED детальный разбор",
    "link": "https://habr.com/ru/companies/X5Tech/articles/780270/",
    "source": "habr",
    "company": "X5",
    "themes": [
      "experiments",
      "variance-reduction"
    ],
    "section": "analytics",
    "summary": "CUPED — метод снижения дисперсии в А/Б тестах через данные до эксперимента: принцип, выбор ковариаты, бинарные метрики.",
    "author": "Nazarov",
    "difficulty": "продвинутый"
  },
  {
    "id": "7",
    "title": "AB тесты с метрикой отношения. Дельта-метод",
    "link": "https://habr.com/ru/companies/X5Tech/articles/740476/",
    "source": "habr",
    "company": "X5",
    "themes": [
      "experiments",
      "metrics"
    ],
    "section": "analytics",
    "summary": "Разбирает метрики отношения (средний чек, CTR) и учит применять дельта-метод для их корректного тестирования в А/Б экспериментах.",
    "author": "Nazarov",
    "difficulty": "продвинутый"
  },
  {
    "id": "8",
    "title": "Бутстрап и АБ тестирование",
    "link": "https://habr.com/ru/companies/X5Tech/articles/679842/",
    "source": "habr",
    "company": "X5",
    "themes": [
      "experiments",
      "statistics"
    ],
    "section": "analytics",
    "summary": "Бутстреп с кодом: оценка стандартных отклонений и доверительных интервалов для квантилей.",
    "author": "Nazarov",
    "difficulty": "продвинутый"
  },
  {
    "id": "9",
    "title": "Определяем оптимальный размер групп при множественном АБ тестировании",
    "link": "https://habr.com/ru/companies/X5Tech/articles/763656/",
    "source": "habr",
    "company": "X5",
    "themes": [
      "experiments",
      "multiple-testing"
    ],
    "section": "analytics",
    "summary": "Как оптимально разбить трафик при общей контрольной группе в нескольких A/B тестах — доказательство через минимизацию дисперсии t-статистики.",
    "author": "Nazarov",
    "difficulty": "продвинутый"
  },
  {
    "id": "10",
    "title": "Как мы запустили платформу для AB-тестирования на 20 000 офлайн-магазинов",
    "link": "https://vc.ru/x5group/758216-kak-my-zapustili-platformu-dlya-a-b-testirovaniya-na-20-000-oflain-magazinov",
    "source": "vc",
    "company": "X5",
    "themes": [
      "experiments"
    ],
    "section": "analytics",
    "summary": "Как X5 Group автоматизировала А/Б-тесты на 20 000 магазинов и сократила время дизайна эксперимента на две недели.",
    "author": null,
    "difficulty": "методология"
  },
  {
    "id": "11",
    "title": "Varioqub за Mann-Whitney замолвите слово",
    "link": "https://habr.com/ru/companies/X5Tech/articles/823078/",
    "source": "habr",
    "company": "X5",
    "themes": [
      "experiments",
      "statistics"
    ],
    "section": "analytics",
    "summary": "Как работает Mann-Whitney под капотом Varioqub: разбор формул, интерпретации и связи с Wilcoxon и Probability Index.",
    "author": null,
    "difficulty": "продвинутый"
  },
  {
    "id": "12",
    "title": "Бутстрап временных рядов",
    "link": "https://habr.com/ru/companies/X5Tech/articles/814579/",
    "source": "habr",
    "company": "X5",
    "themes": [
      "experiments",
      "statistics"
    ],
    "section": "analytics",
    "summary": "Обзор модификаций бутстрапа для временных рядов: почему стандартный метод неприменим и какие альтернативы работают.",
    "author": null,
    "difficulty": "продвинутый"
  },
  {
    "id": "13",
    "title": "Как проводить AB-тестирование на 15 000 офлайн-магазинах",
    "link": "https://habr.com/ru/companies/X5Tech/articles/466349/",
    "source": "habr",
    "company": "X5",
    "themes": [
      "experiments"
    ],
    "section": "analytics",
    "summary": "Методология A/B-тестирования X5 Retail Group для офлайн-магазинов: особенности метрик РТО, трафика и проблемы с выборкой.",
    "author": null,
    "difficulty": "методология"
  },
  {
    "id": "14",
    "title": "Методы балансировки в AB тестировании",
    "link": "https://habr.com/ru/companies/X5Tech/articles/780690/",
    "source": "habr",
    "company": "X5",
    "themes": [
      "experiments",
      "variance-reduction"
    ],
    "section": "analytics",
    "summary": "Обзор методов балансировки для анализа причинности: как устранить смещения при неслучайном распределении объектов по группам.",
    "author": null,
    "difficulty": "методология"
  },
  {
    "id": "15",
    "title": "От AB-тестирования к Causal Inference в оффлайн ритейле",
    "link": "https://habr.com/ru/companies/X5Tech/articles/768008/",
    "source": "habr",
    "company": "X5",
    "themes": [
      "experiments",
      "causality"
    ],
    "section": "analytics",
    "summary": "Почему классические A/B-тесты не работают в офлайн-ритейле и как Causal Inference решает проблему нерандомной выборки.",
    "author": null,
    "difficulty": "продвинутый"
  },
  {
    "id": "16",
    "title": "Стратификация. Как разбиение выборки повышает чувствительность AB теста",
    "link": "https://habr.com/ru/companies/X5Tech/articles/596279/",
    "source": "habr",
    "company": "X5",
    "themes": [
      "experiments",
      "variance-reduction"
    ],
    "section": "analytics",
    "summary": "Объясняет стратифицированное семплирование для снижения дисперсии метрики в A/B-тестах с формулами и примером интернет-магазина.",
    "author": null,
    "difficulty": "продвинутый"
  },
  {
    "id": "17",
    "title": "Diff-in-diff - жизнь за пределами идеального эксперимента",
    "link": "https://habr.com/ru/companies/X5Tech/articles/867734/",
    "source": "habr",
    "company": "X5",
    "themes": [
      "experiments",
      "causality"
    ],
    "section": "analytics",
    "summary": "Объясняет метод difference-in-difference для оценки эффекта воздействия в А/Б тестах, когда идеальный эксперимент невозможен.",
    "author": null,
    "difficulty": "продвинутый"
  },
  {
    "id": "18",
    "title": "Один многорукий бандит против всех AB тестов",
    "link": "https://m.vk.com/@kontur_student-odin-mnogorukii-bandit-protiv-vseh-ab-testov",
    "source": "vk",
    "company": "VK",
    "themes": [
      "experiments"
    ],
    "section": "analytics",
    "summary": "Многорукие бандиты как альтернатива А/Б-тестам: алгоритм сам выбирает лучший вариант фичи без ручного контроля.",
    "author": null,
    "difficulty": "базовый"
  },
  {
    "id": "19",
    "title": "Проектируем AB-эксперименты грамотно",
    "link": "https://habr.com/ru/companies/vk/articles/847088/",
    "source": "habr",
    "company": "VK",
    "themes": [
      "experiments"
    ],
    "section": "analytics",
    "summary": "Как формулировать проверяемые гипотезы для A/B-тестов в мобильных приложениях — для новичков без математики.",
    "author": null,
    "difficulty": "базовый"
  },
  {
    "id": "20",
    "title": "Causal Impact как инструмент аналитика в Uzum",
    "link": "https://habr.com/ru/companies/uzum/articles/817473/",
    "source": "habr",
    "company": "Uzum",
    "themes": [
      "analytics-core",
      "causality"
    ],
    "section": "analytics",
    "summary": "Как оценить эффект изменений без A/B-теста с помощью CausalImpact на примере Uzum Marketplace.",
    "author": null,
    "difficulty": "методология"
  },
  {
    "id": "21",
    "title": "На что мы обращаем внимание при расчете статистической значимости AB-теста",
    "link": "https://habr.com/ru/companies/uchi_ru/articles/500918/",
    "source": "habr",
    "company": "Uchi",
    "themes": [
      "experiments",
      "statistics"
    ],
    "section": "analytics",
    "summary": "Как правильно проводить A/B-тесты: расчёт срока, уровень значимости и защита от ложноположительных результатов.",
    "author": null,
    "difficulty": "методология"
  },
  {
    "id": "22",
    "title": "Оптимизируем AB-тесты - единый шаблон и DIY-инструментарий для аналитиков",
    "link": "https://habr.com/ru/companies/sravni/articles/826244/",
    "source": "habr",
    "company": "Sravni",
    "themes": [
      "experiments"
    ],
    "section": "analytics",
    "summary": "Как Сравни унифицировала A/B-тестирование среди 40 аналитиков и построила автоматизированный инструмент анализа результатов.",
    "author": "Polushkin",
    "difficulty": "продвинутый"
  },
  {
    "id": "23",
    "title": "Особенности и подводные камни ABn-тестирования",
    "link": "https://habr.com/ru/companies/sravni/articles/723662/",
    "source": "habr",
    "company": "Sravni",
    "themes": [
      "experiments",
      "anti-patterns"
    ],
    "section": "analytics",
    "summary": "Как финансовый маркетплейс Сравни переходил с самописной A/B-системы на Sigma: ограничения, подводные камни, рекомендации.",
    "author": "Polushkin",
    "difficulty": "методология"
  },
  {
    "id": "24",
    "title": "Что не так с AB тестированием",
    "link": "https://habr.com/ru/companies/skyeng/articles/440692/",
    "source": "habr",
    "company": "Skyeng",
    "themes": [
      "experiments",
      "anti-patterns"
    ],
    "section": "analytics",
    "summary": "Критика классического A/B-теста: почему выбор одного варианта для всех проигрывает персонализированной комбинации A и B.",
    "author": null,
    "difficulty": "методология"
  },
  {
    "id": "25",
    "title": "«Подземные камни» AB-тестирования в e-commerce",
    "link": "https://habr.com/ru/companies/retailrocket/articles/801667/",
    "source": "habr",
    "company": "RetailRocket",
    "themes": [
      "experiments",
      "anti-patterns"
    ],
    "section": "analytics",
    "summary": "Retail Rocket Group о недооценённых аспектах А/Б-тестов в e-commerce: А/А-тесты, ошибки дизайна и интерпретации.",
    "author": null,
    "difficulty": "методология"
  },
  {
    "id": "26",
    "title": "Подводные камни AB-тестирования или почему 99% ваших сплит-тестов проводятся неверно",
    "link": "https://habr.com/ru/companies/retailrocket/articles/261593/",
    "source": "habr",
    "company": "RetailRocket",
    "themes": [
      "experiments",
      "anti-patterns"
    ],
    "section": "analytics",
    "summary": "Методология A/Б-тестирования для e-commerce: от постановки гипотезы до сравнения доверительных интервалов конверсии.",
    "author": null,
    "difficulty": "методология"
  },
  {
    "id": "27",
    "title": "Проведение AB-тестирования пошаговый разбор",
    "link": "https://habr.com/ru/companies/plarium/articles/526706/",
    "source": "habr",
    "company": "Plarium",
    "themes": [
      "experiments"
    ],
    "section": "analytics",
    "summary": "Шесть шагов A/B-тестирования в играх: как аналитик Plarium выстраивает процесс и обходит типичные ловушки.",
    "author": null,
    "difficulty": "методология"
  },
  {
    "id": "28",
    "title": "Без АB результат XЗ, или Как построить высоконагруженную платформу АB-тестов",
    "link": "https://habr.com/ru/companies/ozontech/articles/689052/",
    "source": "habr",
    "company": "Ozon",
    "themes": [
      "experiments"
    ],
    "section": "analytics",
    "summary": "Как построить платформу А/B-тестов на высоком RPS и измерять влияние фич на бизнес-метрики — на примере Ozon.",
    "author": null,
    "difficulty": "методология"
  },
  {
    "id": "29",
    "title": "Шесть причин, почему ваши AB-тесты не работают",
    "link": "https://habr.com/ru/companies/ozontech/articles/712306/",
    "source": "habr",
    "company": "Ozon",
    "themes": [
      "experiments",
      "anti-patterns"
    ],
    "section": "analytics",
    "summary": "Шесть причин невалидности A/B-тестов: ratio-метрики, множественное тестирование, ранняя остановка и децентрализованный процесс.",
    "author": null,
    "difficulty": "продвинутый"
  },
  {
    "id": "30",
    "title": "Как ускорить AB тесты - несколько способов",
    "link": "https://habr.com/ru/companies/otus/articles/839922/",
    "source": "habr",
    "company": "Otus",
    "themes": [
      "experiments",
      "variance-reduction"
    ],
    "section": "analytics",
    "summary": "Как ускорить A/B тесты с помощью параллельных и многовариантных экспериментов, избегая перекрёстного влияния между группами.",
    "author": null,
    "difficulty": "методология"
  },
  {
    "id": "31",
    "title": "Как организовать процесс АВ тестирования на коленке",
    "link": "https://habr.com/ru/companies/oleg-bunin/articles/836056/",
    "source": "habr",
    "company": "Okko",
    "themes": [
      "experiments"
    ],
    "section": "analytics",
    "summary": "Как выстроить A/B-тестирование без собственной платформы: этапы зрелости и компоненты процесса экспериментов в онлайн-сервисе.",
    "author": null,
    "difficulty": "методология"
  },
  {
    "id": "32",
    "title": "Работа с AB-тестами в крупной соцсети подробно об AB платформе Одноклассников",
    "link": "https://habr.com/ru/companies/odnoklassniki/articles/772958/",
    "source": "habr",
    "company": "OK",
    "themes": [
      "experiments"
    ],
    "section": "analytics",
    "summary": "Как устроена A/B-платформа Одноклассников: роли команд, этапы эксперимента и процесс анализа на 110 тестах в день.",
    "author": null,
    "difficulty": "методология"
  },
  {
    "id": "33",
    "title": "Офлайн AB тестирование в ритейле",
    "link": "https://habr.com/ru/companies/ods/articles/416101/",
    "source": "habr",
    "company": "ODS",
    "themes": [
      "experiments"
    ],
    "section": "analytics",
    "summary": "Как адаптировать А/Б тестирование для офлайн-ритейла с 500+ неоднородными магазинами при смене выкладки товаров.",
    "author": "Nesterov",
    "difficulty": "методология"
  },
  {
    "id": "34",
    "title": "AB тесты — это не только ценный мех… Но еще и процессы",
    "link": "https://habr.com/ru/companies/ods/articles/716110/",
    "source": "habr",
    "company": "ODS",
    "themes": [
      "experiments"
    ],
    "section": "analytics",
    "summary": "Как встроить АБ-тестирование в инвестиционный цикл офлайн-бизнеса: организационные советы без углублённой математики.",
    "author": null,
    "difficulty": "методология"
  },
  {
    "id": "35",
    "title": "Байесовские многорукие бандиты против AB тестов",
    "link": "https://habr.com/ru/companies/ods/articles/325416/",
    "source": "habr",
    "company": "ODS",
    "themes": [
      "experiments",
      "statistics"
    ],
    "section": "analytics",
    "summary": "Объясняет замену A/B/n-теста байесовскими бандитами для максимизации конверсии при минимальном расходе трафика.",
    "author": null,
    "difficulty": "продвинутый"
  },
  {
    "id": "36",
    "title": "Отток в офлайн-ритейле - как увеличить возврат клиентов ПРО на 20%",
    "link": "https://habr.com/ru/companies/leroy_merlin/articles/789760/",
    "source": "habr",
    "company": "LeroyMerlin",
    "themes": [
      "experiments",
      "metrics"
    ],
    "section": "analytics",
    "summary": "ML-продукт для прогнозирования оттока ПРО-клиентов в ритейле: разметка данных, методология A/B-теста и продуктивизация сервиса.",
    "author": null,
    "difficulty": "продвинутый"
  },
  {
    "id": "37",
    "title": "А если без A - B-тестов Как мы оценивали эффективность контент-продукта через квазиэксперименты",
    "link": "https://habr.com/ru/companies/lamoda/articles/869404/",
    "source": "habr",
    "company": "Lamoda",
    "themes": [
      "experiments",
      "causality"
    ],
    "section": "analytics",
    "summary": "Как в Lamoda искали альтернативу A/B-тестам для контентного продукта: модели атрибуции, мэтчинг и их подводные камни.",
    "author": null,
    "difficulty": "методология"
  },
  {
    "id": "38",
    "title": "Как же мощно я провел AB-тест, или почему не стоит сравнивать наблюдаемый аплифт с MDE",
    "link": "https://habr.com/ru/companies/lamoda/articles/728034/",
    "source": "habr",
    "company": "Lamoda",
    "themes": [
      "experiments",
      "anti-patterns"
    ],
    "section": "analytics",
    "summary": "Разбор ошибочного подхода к интерпретации A/B-тестов: почему наблюдаемый аплифт не нужно сравнивать с MDE.",
    "author": null,
    "difficulty": "продвинутый"
  },
  {
    "id": "39",
    "title": "Статистические критерии для начинающих",
    "link": "https://habr.com/ru/companies/kuper/articles/827448/",
    "source": "habr",
    "company": "Kuper",
    "themes": [
      "experiments",
      "statistics"
    ],
    "section": "analytics",
    "summary": "Статистические критерии для A/B-тестов: физический смысл формул и практические кейсы для начинающих аналитиков.",
    "author": null,
    "difficulty": "методология"
  },
  {
    "id": "40",
    "title": "База - айсберг AB тестов",
    "link": "https://habr.com/ru/companies/sbermarket/articles/774608/",
    "source": "habr",
    "company": "Kuper",
    "themes": [
      "experiments"
    ],
    "section": "analytics",
    "summary": "Системная карта AB-тестов сверху вниз: метрики, воронка, преобразования, ошибки 1/2 рода.",
    "author": "Mosin",
    "difficulty": "методология"
  },
  {
    "id": "41",
    "title": "Бутстрап швейцарский нож аналитика в AB-тестах",
    "link": "https://habr.com/ru/articles/762648/",
    "source": "habr",
    "company": "Kuper",
    "themes": [
      "experiments",
      "statistics"
    ],
    "section": "analytics",
    "summary": "Бутстрап для A/B-тестов: как строить доверительные интервалы и считать p-value без параметрических допущений.",
    "author": "Mosin",
    "difficulty": "продвинутый"
  },
  {
    "id": "42",
    "title": "Линеаризация - зачем и как укрощать ratio-метрики в AB-тестах",
    "link": "https://habr.com/ru/companies/sbermarket/articles/768826/",
    "source": "habr",
    "company": "Kuper",
    "themes": [
      "experiments",
      "metrics"
    ],
    "section": "analytics",
    "summary": "Линеаризация ratio-метрик в A/B-тестах: переход к независимым наблюдениям для корректного применения t-теста.",
    "author": "Mosin",
    "difficulty": "продвинутый"
  },
  {
    "id": "43",
    "title": "Коварные перцентильные фильтры",
    "link": "https://habr.com/ru/companies/hh/articles/670376/",
    "source": "habr",
    "company": "HH",
    "themes": [
      "experiments",
      "anti-patterns"
    ],
    "section": "analytics",
    "summary": "Как аналитики hh.ru чуть не попали в ловушку самообмана при анализе A/B-эксперимента с метрикой откликов.",
    "author": null,
    "difficulty": "продвинутый"
  },
  {
    "id": "44",
    "title": "Causal Inference from Observational Data, или как провести АВ-тест без АВ-теста",
    "link": "https://koch-kir.medium.com/causal-inference-from-observational-data-%D0%B8%D0%BB%D0%B8-%D0%BA%D0%B0%D0%BA-%D0%BF%D1%80%D0%BE%D0%B2%D0%B5%D1%81%D1%82%D0%B8-%D0%B0-%D0%B2-%D1%82%D0%B5%D1%81%D1%82-%D0%B1%D0%B5%D0%B7-%D0%B0-%D0%B2-%D1%82%D0%B5%D1%81%D1%82%D0%B0-afb84f2579f2",
    "source": "medium",
    "company": "HH",
    "themes": [
      "experiments",
      "causality"
    ],
    "section": "analytics",
    "summary": "Введение в причинно-следственный анализ: фреймворки PO и SCM, отличие от ML-ассоциаций, задачи uplift-моделирования и прокси-метрик.",
    "author": "Kochnev",
    "difficulty": "методология"
  },
  {
    "id": "45",
    "title": "Байесовский подход к AB тестированию",
    "link": "https://habr.com/ru/companies/glowbyte/articles/732024/",
    "source": "habr",
    "company": "Glowbyte",
    "themes": [
      "experiments",
      "statistics"
    ],
    "section": "analytics",
    "summary": "Альтернатива p-value: бета-распределения, апостериорные вероятности, гибкие сроки теста.",
    "author": null,
    "difficulty": "методология"
  },
  {
    "id": "46",
    "title": "Как подготовить и провести AB-тестирование. Базовый роадмэп для новичков",
    "link": "https://habr.com/ru/companies/glowbyte/articles/696540/",
    "source": "habr",
    "company": "Glowbyte",
    "themes": [
      "experiments"
    ],
    "section": "analytics",
    "summary": "Роадмэп A/B-теста из 4 этапов: планирование, подготовка групп, запуск и анализ — для тех, кто только входит в тему.",
    "author": null,
    "difficulty": "методология"
  },
  {
    "id": "47",
    "title": "Оценка эффекта персонализации баннеров в Альфа-Банке с применением библиотеки Kolmogorov ABacus",
    "link": "https://habr.com/ru/companies/glowbyte/articles/762164/",
    "source": "habr",
    "company": "Glowbyte",
    "themes": [
      "experiments"
    ],
    "section": "analytics",
    "summary": "Разбор кейса Альфа-Банка: почему ML-модель персонализации не показала эффекта в A/B-тесте и как найти ошибки дизайна эксперимента.",
    "author": null,
    "difficulty": "продвинутый"
  },
  {
    "id": "48",
    "title": "Вся основная теория по AB-экспериментам Лоладзе + expf",
    "link": "https://colab.research.google.com/drive/1_CY_8DJRLm70gl9RjTz1vmPoLMwCeT0u",
    "source": "other",
    "company": "expf",
    "themes": [
      "experiments",
      "statistics"
    ],
    "section": "analytics",
    "summary": "Конспект 20 ч. лекций по А/Б-тестам: типы экспериментов, дерево метрик, ошибки 1-го и 2-го рода.",
    "author": "Илья Лоладзе",
    "difficulty": "методология"
  },
  {
    "id": "49",
    "title": "CUPED или увеличение чувствительности метрики",
    "link": "https://medium.com/statistics-experiments/cuped-%D0%B8%D0%BB%D0%B8-%D1%83%D0%B2%D0%B5%D0%BB%D0%B8%D1%87%D0%B5%D0%BD%D0%B8%D0%B5-%D1%87%D1%83%D0%B2%D1%81%D1%82%D0%B2%D0%B8%D1%82%D0%B5%D0%BB%D1%8C%D0%BD%D0%BE%D1%81%D1%82%D0%B8-%D0%BC%D0%B5%D1%82%D1%80%D0%B8%D0%BA%D0%B8-de7183fc964c",
    "source": "medium",
    "company": "expf",
    "themes": [
      "experiments",
      "variance-reduction"
    ],
    "section": "analytics",
    "summary": "Базовый разбор CUPED: как ковариата до эксперимента сокращает дисперсию на 30–70%.",
    "author": null,
    "difficulty": "продвинутый"
  },
  {
    "id": "50",
    "title": "Switchback-тестирование. Как бороться с социальными эффектами в AB-тестах",
    "link": "https://medium.com/statistics-experiments/switchback-%D1%82%D0%B5%D1%81%D1%82%D0%B8%D1%80%D0%BE%D0%B2%D0%B0%D0%BD%D0%B8%D0%B5-%D0%BA%D0%B0%D0%BA-%D0%B1%D0%BE%D1%80%D0%BE%D1%82%D1%8C%D1%81%D1%8F-%D1%81-%D1%81%D0%BE%D1%86%D0%B8%D0%B0%D0%BB%D1%8C%D0%BD%D1%8B%D0%BC%D0%B8-%D1%8D%D1%84%D1%84%D0%B5%D0%BA%D1%82%D0%B0%D0%BC%D0%B8-%D0%B2-a-b-%D1%82%D0%B5%D1%81%D1%82%D0%B0%D1%85-39aab4f87cf7",
    "source": "medium",
    "company": "expf",
    "themes": [
      "experiments"
    ],
    "section": "analytics",
    "summary": "Что такое свитчбэк-тестирование и как оно решает проблему network effects при A/B-экспериментах в маркетплейсах.",
    "author": null,
    "difficulty": "методология"
  },
  {
    "id": "51",
    "title": "Децильный метод или сокращение дисперсии",
    "link": "https://medium.com/statistics-experiments/%D0%B4%D0%B5%D1%86%D0%B8%D0%BB%D1%8C%D0%BD%D1%8B%D0%B9-%D0%BC%D0%B5%D1%82%D0%BE%D0%B4-%D0%B8%D0%BB%D0%B8-%D1%81%D0%BE%D0%BA%D1%80%D0%B0%D1%89%D0%B5%D0%BD%D0%B8%D0%B5-%D0%B4%D0%B8%D1%81%D0%BF%D0%B5%D1%80%D1%81%D0%B8%D0%B8-c06758059727",
    "source": "medium",
    "company": "expf",
    "themes": [
      "experiments",
      "variance-reduction"
    ],
    "section": "analytics",
    "summary": "Децильный анализ как метод снижения дисперсии в A/B-тестах на монетизации без удаления выбросов.",
    "author": null,
    "difficulty": "методология"
  },
  {
    "id": "52",
    "title": "Дисбаланс в AB-тестах. Есть ли разница между 99%-1% и 50%-50% в экспериментах",
    "link": "https://medium.com/statistics-experiments/%D0%B4%D0%B8%D1%81%D0%B1%D0%B0%D0%BB%D0%B0%D0%BD%D1%81-%D0%B2-a-b-%D1%82%D0%B5%D1%81%D1%82%D0%B0%D1%85-%D0%B5%D1%81%D1%82%D1%8C-%D0%BB%D0%B8-%D1%80%D0%B0%D0%B7%D0%BD%D0%B8%D1%86%D0%B0-%D0%BC%D0%B5%D0%B6%D0%B4%D1%83-99-1-%D0%B8-50-50-%D0%B2-%D1%8D%D0%BA%D1%81%D0%BF%D0%B5%D1%80%D0%B8%D0%BC%D0%B5%D0%BD%D1%82%D0%B0%D1%85-11c8f4fe7eb4",
    "source": "medium",
    "company": "expf",
    "themes": [
      "experiments"
    ],
    "section": "analytics",
    "summary": "Нюансы планирования несбалансированных A/B-тестов (90/10, 99/1): мощность критерия, ошибка II рода и симуляции.",
    "author": null,
    "difficulty": "продвинутый"
  },
  {
    "id": "53",
    "title": "Когда останавливать AB-тест. Часть 1 MDE",
    "link": "https://medium.com/statistics-experiments/%D0%BA%D0%BE%D0%B3%D0%B4%D0%B0-%D0%BE%D1%81%D1%82%D0%B0%D0%BD%D0%B0%D0%B2%D0%BB%D0%B8%D0%B2%D0%B0%D1%82%D1%8C-a-b-%D1%82%D0%B5%D1%81%D1%82-%D1%87%D0%B0%D1%81%D1%82%D1%8C-1-mde-7d39b668b488",
    "source": "medium",
    "company": "expf",
    "themes": [
      "experiments",
      "statistics"
    ],
    "section": "analytics",
    "summary": "Как выбрать момент остановки AB-теста: Fixed Horizon vs Sequential testing и ключевые статистические факторы.",
    "author": null,
    "difficulty": "продвинутый"
  },
  {
    "id": "54",
    "title": "Когда останавливать AB-тест. Часть 2 Monte Carlo",
    "link": "https://medium.com/statistics-experiments/%D0%BA%D0%BE%D0%B3%D0%B4%D0%B0-%D0%BE%D1%81%D1%82%D0%B0%D0%BD%D0%B0%D0%B2%D0%BB%D0%B8%D0%B2%D0%B0%D1%82%D1%8C-a-b-%D1%82%D0%B5%D1%81%D1%82-%D1%87%D0%B0%D1%81%D1%82%D1%8C-2-monte-carlo-a342ba5b552c",
    "source": "medium",
    "company": "expf",
    "themes": [
      "experiments",
      "statistics"
    ],
    "section": "analytics",
    "summary": "Как рассчитать MDE для A/B-теста и применять Monte Carlo-симуляции для оценки чувствительности нестандартных метрик.",
    "author": null,
    "difficulty": "продвинутый"
  },
  {
    "id": "55",
    "title": "Случайность над случайностью или в поисках \"Социального эффекта\"",
    "link": "https://medium.com/statistics-experiments/%D1%81%D0%BB%D1%83%D1%87%D0%B0%D0%B9%D0%BD%D0%BE%D1%81%D1%82%D1%8C-%D0%BD%D0%B0%D0%B4-%D1%81%D0%BB%D1%83%D1%87%D0%B0%D0%B9%D0%BD%D0%BE%D1%81%D1%82%D1%8C%D1%8E-%D0%B8%D0%BB%D0%B8-%D0%B2-%D0%BF%D0%BE%D0%B8%D1%81%D0%BA%D0%B0%D1%85-%D1%81%D0%BE%D1%86%D0%B8%D0%B0%D0%BB%D1%8C%D0%BD%D0%BE%D0%B3%D0%BE-%D1%8D%D1%84%D1%84%D0%B5%D0%BA%D1%82%D0%B0-e3aa29ef9053",
    "source": "medium",
    "company": "expf",
    "themes": [
      "experiments"
    ],
    "section": "analytics",
    "summary": "Метод обнаружения сетевого эффекта в A/B-тестах через параллельный запуск классического и кластерного дизайнов по статье LinkedIn.",
    "author": null,
    "difficulty": "методология"
  },
  {
    "id": "56",
    "title": "Увеличиваем чувствительность экспериментов при помощи ранговой трансформации",
    "link": "https://medium.com/statistics-experiments/%D1%83%D0%B2%D0%B5%D0%BB%D0%B8%D1%87%D0%B8%D0%B2%D0%B0%D0%B5%D0%BC-%D1%87%D1%83%D0%B2%D1%81%D1%82%D0%B2%D0%B8%D1%82%D0%B5%D0%BB%D1%8C%D0%BD%D0%BE%D1%81%D1%82%D1%8C-%D1%8D%D0%BA%D1%81%D0%BF%D0%B5%D1%80%D0%B8%D0%BC%D0%B5%D0%BD%D1%82%D0%BE%D0%B2-%D0%BF%D1%80%D0%B8-%D0%BF%D0%BE%D0%BC%D0%BE%D1%89%D0%B8-%D1%80%D0%B0%D0%BD%D0%B3%D0%BE%D0%B2%D0%BE%D0%B9-%D1%82%D1%80%D0%B0%D0%BD%D1%81%D1%84%D0%BE%D1%80%D0%BC%D0%B0%D1%86%D0%B8%D0%B8-32a4f72a86fc",
    "source": "medium",
    "company": "expf",
    "themes": [
      "experiments",
      "variance-reduction"
    ],
    "section": "analytics",
    "summary": "Метод трансформации метрик для повышения чувствительности A/B тестов при ненормальном распределении данных в Booking.com.",
    "author": null,
    "difficulty": "продвинутый"
  },
  {
    "id": "57",
    "title": "Как мы научились АB-тестировать алгоритмы с помощью switchback-тестов",
    "link": "https://habr.com/ru/companies/deliveryclub/articles/670762/",
    "source": "habr",
    "company": "DeliveryClub",
    "themes": [
      "experiments"
    ],
    "section": "analytics",
    "summary": "Switchback A/B-тесты в логистике: как бороться с сетевыми эффектами при назначении курьеров на примере Delivery Club.",
    "author": null,
    "difficulty": "методология"
  },
  {
    "id": "58",
    "title": "Эксперименты в Ситимобил. Эпизод 1 Скрытая сила switchback",
    "link": "https://habr.com/ru/companies/citymobil/articles/560426/",
    "source": "habr",
    "company": "Citymobil",
    "themes": [
      "experiments"
    ],
    "section": "analytics",
    "summary": "Объясняет, почему классические A/B-тесты не работают в маркетплейсах, и вводит switchback как альтернативу.",
    "author": null,
    "difficulty": "методология"
  },
  {
    "id": "59",
    "title": "Эксперименты в Ситимобил. Эпизод 2 Атака тестов на Switchback",
    "link": "https://habr.com/ru/companies/citymobil/articles/575218/",
    "source": "habr",
    "company": "Citymobil",
    "themes": [
      "experiments"
    ],
    "section": "analytics",
    "summary": "Сравнение статистических тестов для switchback-экспериментов в маркетплейсе: выбор агрегации и метода проверки гипотез.",
    "author": null,
    "difficulty": "продвинутый"
  },
  {
    "id": "60",
    "title": "Как устроено AB-тестирование в Авито",
    "link": "https://habr.com/ru/companies/avito/articles/454164/",
    "source": "habr",
    "company": "Avito",
    "themes": [
      "experiments"
    ],
    "section": "analytics",
    "summary": "Архитектура платформы A/B-тестирования Авито: конфигурация экспериментов, хеш-сплиттинг трафика, сбор метрик и визуализация.",
    "author": "Lenkov",
    "difficulty": "методология"
  },
  {
    "id": "61",
    "title": "ML-критерии для AB-тестов",
    "link": "https://habr.com/ru/companies/avito/articles/590105/",
    "source": "habr",
    "company": "Avito",
    "themes": [
      "experiments",
      "statistics"
    ],
    "section": "analytics",
    "summary": "Как применять ML-методы (CUPAC, CUMPED, Uplift-модели) для повышения мощности A/B-критериев — от CUPED до объединённых критериев.",
    "author": "Lunin",
    "difficulty": "экспертный"
  },
  {
    "id": "62",
    "title": "Как улучшить ваши AB-тесты - лайфхаки аналитиков Авито. Часть 1",
    "link": "https://habr.com/ru/companies/avito/articles/571094/",
    "source": "habr",
    "company": "Avito",
    "themes": [
      "experiments"
    ],
    "section": "analytics",
    "summary": "CUPED, бутстрап и стратификация для повышения мощности A/B-тестов — с проверкой методов и борьбой с выбросами.",
    "author": "Lunin",
    "difficulty": "продвинутый"
  },
  {
    "id": "63",
    "title": "Как улучшить ваши AB-тесты - лайфхаки аналитиков Авито. Часть 2",
    "link": "https://habr.com/ru/companies/avito/articles/571096/",
    "source": "habr",
    "company": "Avito",
    "themes": [
      "experiments"
    ],
    "section": "analytics",
    "summary": "Методы увеличения мощности A/B-тестов: CUPED, бутстрап-критерии, стратификация и парная стратификация — вторая часть цикла Avito.",
    "author": "Lunin",
    "difficulty": "продвинутый"
  },
  {
    "id": "64",
    "title": "Критерий Манна-Уитни — самый главный враг AB-тестов",
    "link": "https://habr.com/ru/companies/avito/articles/709596/",
    "source": "habr",
    "company": "Avito",
    "themes": [
      "experiments",
      "statistics",
      "anti-patterns"
    ],
    "section": "analytics",
    "summary": "Развенчание мифа: Манн-Уитни не сравнивает средние/медианы и даёт ложные прокрасы.",
    "author": "Lunin",
    "difficulty": "экспертный"
  },
  {
    "id": "65",
    "title": "AB тесты и подводные камни при их автоматизации",
    "link": "https://habr.com/ru/articles/781060/",
    "source": "habr",
    "company": "independent",
    "themes": [
      "experiments",
      "anti-patterns"
    ],
    "section": "analytics",
    "summary": "Разбор рисков полной автоматизации А/Б-тестов: почему исключение аналитика создаёт скрытые проблемы с пересечением экспериментов.",
    "author": "Yuldashev",
    "difficulty": "методология"
  },
  {
    "id": "66",
    "title": "Как делить пользователей на группы в AB-тестах ошибки и рекомендации",
    "link": "https://habr.com/ru/articles/800809/",
    "source": "habr",
    "company": "independent",
    "themes": [
      "experiments",
      "anti-patterns"
    ],
    "section": "analytics",
    "summary": "Принципы сплитования в A/B тестах: проблемы случайного деления и подходы к корректному разбиению на группы.",
    "author": "Yuldashev",
    "difficulty": "методология"
  },
  {
    "id": "67",
    "title": "Видео 4 продвинутых способа испортить АБ-тест Бабаев Муслим",
    "link": "https://www.youtube.com/watch?v=Lsa68fzeOKA",
    "source": "youtube",
    "company": "independent",
    "themes": [
      "experiments",
      "anti-patterns"
    ],
    "section": "analytics",
    "summary": "Муслим Бабаев разбирает 4 ошибки в A/B-тестах, из-за которых корректно настроенный тест всё равно даёт ложные выводы.",
    "author": null,
    "difficulty": "методология"
  },
  {
    "id": "68",
    "title": "Анализ экспериментов с Ratio-метриками",
    "link": "https://t.me/zasql_python/301",
    "source": "telegram",
    "company": "independent",
    "themes": [
      "experiments",
      "metrics"
    ],
    "section": "analytics",
    "summary": "Как тестировать метрики-отношения (CTR, средний чек) в A/B: бутстрап, бакетизация и дельта-метод с кодом на Python.",
    "author": null,
    "difficulty": "продвинутый"
  },
  {
    "id": "69",
    "title": "Practitioner's Guide to Statistical Tests",
    "link": "https://vkteam.medium.com/practitioners-guide-to-statistical-tests-ed2d580ef04f",
    "source": "medium",
    "company": "VK",
    "themes": [
      "experiments",
      "statistics"
    ],
    "section": "analytics",
    "summary": "Сравнение статтестов (t-test, Манн-Уитни, bootstrap, дельта-метод) для A/B-экспериментов с CTR — с кодом на Python.",
    "author": null,
    "difficulty": "продвинутый"
  },
  {
    "id": "70",
    "title": "Бутстрап и доверительные интервалы от теории к практике на Python",
    "link": "https://habr.com/ru/articles/829336/",
    "source": "habr",
    "company": "independent",
    "themes": [
      "experiments",
      "statistics"
    ],
    "section": "analytics",
    "summary": "Объясняет метод бутстрапа: как псевдовыборки с повторением позволяют оценивать статистики без знания распределения данных.",
    "author": null,
    "difficulty": "методология"
  },
  {
    "id": "71",
    "title": "Как спорить про результаты AB тестирования",
    "link": "https://habr.com/ru/articles/681416/",
    "source": "habr",
    "company": "independent",
    "themes": [
      "experiments"
    ],
    "section": "analytics",
    "summary": "Практические аргументы для продакт-менеджера, чтобы оспорить зелёные результаты A/B теста и не запустить опасную фичу.",
    "author": null,
    "difficulty": "методология"
  },
  {
    "id": "72",
    "title": "Увеличиваем размер выборки и прокрашиваем серые метрики неочевидная ошибка при проведении АB тестов",
    "link": "https://habr.com/ru/articles/859088/",
    "source": "habr",
    "company": "independent",
    "themes": [
      "experiments",
      "anti-patterns"
    ],
    "section": "analytics",
    "summary": "Разбор проблем использования «магазин-день» как единицы анализа в А/Б-тестах: негативные последствия с кодом и графиками.",
    "author": null,
    "difficulty": "продвинутый"
  },
  {
    "id": "73",
    "title": "Ухудшающие AB-тесты — самый недооцененный инструмент менеджера продукта",
    "link": "https://gopractice.ru/data/ab-test/",
    "source": "gopractice",
    "company": "independent",
    "themes": [
      "experiments"
    ],
    "section": "analytics",
    "summary": "Ухудшающие A/B тесты: как намеренно замедлить продукт, чтобы дёшево проверить влияние скорости на ключевые метрики.",
    "author": null,
    "difficulty": "методология"
  },
  {
    "id": "74",
    "title": "Поиск идеального поиска как устроены поисковые эксперименты на Юле",
    "link": "https://habr.com/ru/companies/youla/articles/675366/",
    "source": "habr",
    "company": "Yula",
    "themes": [
      "analytics-core",
      "experiments"
    ],
    "section": "analytics",
    "summary": "Как команда Юлы проводит поисковые эксперименты: типы поиска, группы задач и метрики для оценки качества выдачи.",
    "author": null,
    "difficulty": "методология"
  },
  {
    "id": "75",
    "title": "Когнитивные искажения у аналитика данных - найти и починить",
    "link": "https://habr.com/ru/companies/yandex_praktikum/articles/795213/",
    "source": "habr",
    "company": "YandexPraktikum",
    "themes": [
      "analytics-core",
      "anti-patterns"
    ],
    "section": "analytics",
    "summary": "Когнитивное искажение WYSIATI при df.head() и три способа улучшить предобработку данных.",
    "author": null,
    "difficulty": "методология"
  },
  {
    "id": "76",
    "title": "Кейс разметка приложения с нуля на конкретном примере",
    "link": "https://habr.com/ru/companies/X5Tech/articles/797185/",
    "source": "habr",
    "company": "X5",
    "themes": [
      "analytics-core",
      "metrics"
    ],
    "section": "analytics",
    "summary": "Как X5 Tech выбрала AppMetrica для гибридного приложения Пятёрочки и выстроила архитектуру разметки событий.",
    "author": null,
    "difficulty": "методология"
  },
  {
    "id": "77",
    "title": "Планирование смен сотрудников в офлайн ритейле как упорядочить хаос",
    "link": "https://habr.com/ru/companies/X5Tech/articles/812093/",
    "source": "habr",
    "company": "X5",
    "themes": [
      "analytics-core"
    ],
    "section": "analytics",
    "summary": "Методология X5 для планирования смен 378 тыс. сотрудников офлайн-магазинов: анализ, прогноз и оптимизация расписания.",
    "author": null,
    "difficulty": "методология"
  },
  {
    "id": "78",
    "title": "Различные вычисления, многопоточность, асинхронность и мультипроцессность в Python",
    "link": "https://habr.com/ru/companies/sberbank/articles/829098/",
    "source": "habr",
    "company": "Sber",
    "themes": [
      "analytics-core"
    ],
    "section": "analytics",
    "summary": "Сравнение многопоточности, мультипроцессности и asyncio в Python с разбором GIL, типов нагрузок и типичных ошибок.",
    "author": null,
    "difficulty": "продвинутый"
  },
  {
    "id": "79",
    "title": "Как удерживать пользователей в мобильных играх",
    "link": "https://habr.com/ru/companies/magnus-tech/articles/837602/",
    "source": "habr",
    "company": "Magnus",
    "themes": [
      "analytics-core",
      "metrics"
    ],
    "section": "analytics",
    "summary": "Что такое удержание игроков в мобильных играх, почему оно критично для ROI и как его повышать.",
    "author": null,
    "difficulty": "базовый"
  },
  {
    "id": "80",
    "title": "Уроки, извлеченные из масштабирования до многотерабайтных датасетов",
    "link": "https://habr.com/ru/companies/magnus-tech/articles/834506/",
    "source": "habr",
    "company": "Magnus",
    "themes": [
      "analytics-core"
    ],
    "section": "analytics",
    "summary": "Практические приёмы масштабирования многотерабайтных датасетов на одной машине и кластере с Joblib и GNU Parallel.",
    "author": null,
    "difficulty": "продвинутый"
  },
  {
    "id": "81",
    "title": "Как мы посчитали уровень Data Drivenности в компании и вклад в него каждого аналитика",
    "link": "https://habr.com/ru/companies/kuper/articles/745868/",
    "source": "habr",
    "company": "Kuper",
    "themes": [
      "analytics-core"
    ],
    "section": "analytics",
    "summary": "Опыт СберМаркета по оцифровке data-культуры: как выбрать метрику зрелости аналитики и управлять ею в компании.",
    "author": null,
    "difficulty": "методология"
  },
  {
    "id": "82",
    "title": "Мир за пределами Pandas - достойные альтернативы для работы с данными",
    "link": "https://habr.com/ru/companies/ru_mts/articles/868388/",
    "source": "habr",
    "company": "KION",
    "themes": [
      "analytics-core"
    ],
    "section": "analytics",
    "summary": "Обзор альтернатив Pandas (Polars, DuckDB, Modin, Vaex) с бенчмарками производительности для выбора подходящего инструмента.",
    "author": null,
    "difficulty": "базовый"
  },
  {
    "id": "83",
    "title": "Метрики продуктового дизайна в Домклик",
    "link": "https://habr.com/ru/companies/domclick/articles/828034/",
    "source": "habr",
    "company": "Domclick",
    "themes": [
      "analytics-core",
      "metrics"
    ],
    "section": "analytics",
    "summary": "Обзор базовых продуктовых метрик (DAU, MAU, Retention, CTR, ER и др.) с простыми примерами расчёта.",
    "author": null,
    "difficulty": "базовый"
  },
  {
    "id": "84",
    "title": "Как оценка актуальности резюме помогла работодателям эффективнее находить кандидатов",
    "link": "https://habr.com/ru/companies/avito/articles/802161/",
    "source": "habr",
    "company": "Avito",
    "themes": [
      "analytics-core"
    ],
    "section": "analytics",
    "summary": "Как в Авито Работе разработали ML-модель оценки актуальности резюме, чтобы снизить долю неактуальных анкет в выдаче.",
    "author": null,
    "difficulty": "методология"
  },
  {
    "id": "85",
    "title": "Типичные задачи аналитика данных. Часть 1. Упала метрика",
    "link": "https://habr.com/ru/articles/787098/",
    "source": "habr",
    "company": "independent",
    "themes": [
      "analytics-core",
      "metrics"
    ],
    "section": "analytics",
    "summary": "Как оценить падение метрики без А/Б теста: выбор релевантной метрики, базы сравнения и порог достаточности данных.",
    "author": "Yuldashev",
    "difficulty": "продвинутый"
  },
  {
    "id": "86",
    "title": "Типичные задачи аналитика. Часть 2. А есть ли тренд",
    "link": "https://habr.com/ru/articles/795251/",
    "source": "habr",
    "company": "independent",
    "themes": [
      "analytics-core",
      "statistics"
    ],
    "section": "analytics",
    "summary": "Как обнаруживать тренды во временных рядах для корректного A/B-тестирования: разбор визуального анализа и его ограничений.",
    "author": "Yuldashev",
    "difficulty": "продвинутый"
  },
  {
    "id": "87",
    "title": "OKR, Дерево Метрик и North Star Metric как выйти из матрицы и прийти к прорывным целям",
    "link": "https://vc.ru/flood/557353-okr-derevo-metrik-i-north-star-metric-kak-vyiti-iz-matricy-i-priiti-k-proryvnym-celyam",
    "source": "vc",
    "company": "independent",
    "themes": [
      "analytics-core",
      "metrics"
    ],
    "section": "analytics",
    "summary": "Как интегрировать OKR, Дерево метрик и North Star Metric для постановки амбициозных целей в команде и компании.",
    "author": null,
    "difficulty": "методология"
  },
  {
    "id": "88",
    "title": "Почему в Авито сильная аналитическая культура 6 главных принципов команды Недвижимости",
    "link": "https://vc.ru/hr/1185398-pochemu-v-avito-silnaya-analiticheskaya-kultura-6-glavnyh-principov-komandy-nedvizhimosti",
    "source": "vc",
    "company": "Avito",
    "themes": [
      "analytics-core"
    ],
    "section": "analytics",
    "summary": "Авито Недвижимость о развитии аналитической культуры: принципы работы команды, задачи аналитиков и карьерные перспективы.",
    "author": null,
    "difficulty": "базовый"
  },
  {
    "id": "89",
    "title": "Баланс стоимости предметов в RPG с помощью линейной алгебры",
    "link": "https://habr.com/ru/articles/836776/",
    "source": "habr",
    "company": "independent",
    "themes": [
      "analytics-core"
    ],
    "section": "analytics",
    "summary": "Как применить линейную алгебру и метод наименьших квадратов для балансировки стоимости предметов в RPG-играх.",
    "author": null,
    "difficulty": "продвинутый"
  },
  {
    "id": "90",
    "title": "Как аналитика помогает разработать игры, которые понимают своих игроков",
    "link": "https://habr.com/ru/companies/serverspace/articles/857988/",
    "source": "habr",
    "company": "independent",
    "themes": [
      "analytics-core"
    ],
    "section": "analytics",
    "summary": "Как аналитика данных помогает разработчикам балансировать геймплей и удерживать игроков — на примерах популярных игр.",
    "author": null,
    "difficulty": "базовый"
  },
  {
    "id": "91",
    "title": "Как не заблудиться в четырех соснах выбираем способ найти причинно-следственную связь без экспериментов",
    "link": "https://habr.com/ru/companies/vkusvill/articles/843744/",
    "source": "habr",
    "company": "VkusVill",
    "themes": [
      "analytics-core",
      "causality"
    ],
    "section": "analytics",
    "summary": "Четыре метода квазиэкспериментов (DiD и др.) для оценки эффекта фичи без A/B-теста — идеи, предпосылки и кейсы из практики.",
    "author": null,
    "difficulty": "методология"
  },
  {
    "id": "92",
    "title": "Как с нуля построить систему обработки событий",
    "link": "https://habr.com/ru/companies/ctsg/articles/842186/",
    "source": "habr",
    "company": "independent",
    "themes": [
      "analytics-core"
    ],
    "section": "analytics",
    "summary": "Архитектура потоковой обработки 80к событий/сек с обогащением данных и выявлением аномалий для UEBA-продукта.",
    "author": null,
    "difficulty": "методология"
  },
  {
    "id": "93",
    "title": "Основы чистого кода на Python (PEP8, SOLID, ООП) часть 1",
    "link": "https://habr.com/ru/articles/836678/",
    "source": "habr",
    "company": "independent",
    "themes": [
      "analytics-core"
    ],
    "section": "analytics",
    "summary": "Введение в чистый Python-код: дзен питона, PEP8, архитектурные паттерны и методологии для новичков, желающих писать поддерживаемый код.",
    "author": null,
    "difficulty": "базовый"
  },
  {
    "id": "94",
    "title": "Парадоксы в данных, и почему визуализация бывает необходима",
    "link": "https://habr.com/ru/articles/804441/",
    "source": "habr",
    "company": "independent",
    "themes": [
      "analytics-core",
      "statistics"
    ],
    "section": "analytics",
    "summary": "Объясняет феномен Уилла Роджерса и похожие парадоксы средних на числовых примерах без сложной математики.",
    "author": null,
    "difficulty": "базовый"
  },
  {
    "id": "95",
    "title": "Стандартных метрик уже недостаточно - как найти и удержать ядро своей mid-core игры",
    "link": "https://habr.com/ru/companies/mygames/articles/667332/",
    "source": "habr",
    "company": "MyGames",
    "themes": [
      "analytics-core",
      "metrics"
    ],
    "section": "analytics",
    "summary": "Как анализировать ядро аудитории мобильной игры через LTV и вовлечённость вместо стандартного набора метрик.",
    "author": null,
    "difficulty": "методология"
  },
  {
    "id": "96",
    "title": "Эффект бабочки и рынки (ч.1)",
    "link": "https://habr.com/ru/articles/803783/",
    "source": "habr",
    "company": "independent",
    "themes": [
      "analytics-core"
    ],
    "section": "analytics",
    "summary": "Объясняет эффект бабочки через примеры из фантастики и историю концепции нелинейности — для понимания непредсказуемости сложных систем.",
    "author": null,
    "difficulty": "базовый"
  },
  {
    "id": "97",
    "title": "Как считать Retention rate Nday Retention, Rolling Retention и другие способы расчета Retention",
    "link": "https://gopractice.ru/product/nday-retention-rollling-retention/",
    "source": "gopractice",
    "company": "independent",
    "themes": [
      "analytics-core",
      "metrics"
    ],
    "section": "analytics",
    "summary": "Разбор методов расчёта Retention (Day N, Rolling и др.) и как выбор метода искажает метрику и решения.",
    "author": null,
    "difficulty": "методология"
  },
  {
    "id": "98",
    "title": "Когортный анализ. Метрики продукта vs метрики роста",
    "link": "https://gopractice.ru/product/cohort_analysis/",
    "source": "gopractice",
    "company": "independent",
    "themes": [
      "analytics-core",
      "metrics"
    ],
    "section": "analytics",
    "summary": "Объясняет суть когортного анализа и чем метрики роста (DAU, MAU) отличаются от продуктовых метрик.",
    "author": null,
    "difficulty": "методология"
  },
  {
    "id": "99",
    "title": "Event Driven Management",
    "link": "https://t.me/quant_valerian/679",
    "source": "telegram",
    "company": "independent",
    "themes": [
      "leadership"
    ],
    "section": "leadership",
    "summary": "Статья описывает подход к управлению продуктом на основе событий и помогает выстроить реактивную систему принятия решений.",
    "difficulty": "методология"
  },
  {
    "id": "100",
    "title": "Быть или не быть тимлидом: разбираем на пальцах",
    "link": "https://habr.com/ru/companies/yandex360/articles/829732/",
    "source": "habr",
    "company": "yandex360",
    "themes": [
      "leadership",
      "career"
    ],
    "section": "leadership",
    "summary": "Статья помогает разобраться, стоит ли становиться тимлидом, и что это означает на практике.",
    "difficulty": "базовый"
  },
  {
    "id": "101",
    "title": "Джун, сеньор и мидл — меняются ли представления о грейдах",
    "link": "https://habr.com/ru/companies/netologyru/articles/812871/",
    "source": "habr",
    "company": "netology",
    "themes": [
      "career"
    ],
    "section": "leadership",
    "summary": "Статья разбирает, как меняются критерии и ожидания к грейдам джун/мидл/сеньор в IT-индустрии.",
    "difficulty": "базовый"
  },
  {
    "id": "102",
    "title": "Заметки менеджера из Anthropic",
    "link": "https://t.me/blog_toxa/381",
    "source": "telegram",
    "company": "independent",
    "themes": [
      "leadership",
      "processes"
    ],
    "section": "leadership",
    "summary": "Личные заметки менеджера из Anthropic — инсайты и практический опыт управления в AI-компании.",
    "difficulty": "методология"
  },
  {
    "id": "103",
    "title": "Инструкция для начинающих руководителей",
    "link": "https://habr.com/ru/companies/selectel/articles/690200/",
    "source": "habr",
    "company": "selectel",
    "themes": [
      "leadership"
    ],
    "section": "leadership",
    "summary": "Практическое руководство для новых руководителей: основные принципы управления командой и типичные ошибки на старте.",
    "difficulty": "базовый"
  },
  {
    "id": "104",
    "title": "Как начать руководить незнакомой IT-командой",
    "link": "https://www.youtube.com/watch?v=dRqPca-BG6E",
    "source": "youtube",
    "company": "independent",
    "themes": [
      "leadership",
      "team"
    ],
    "section": "leadership",
    "summary": "Практические советы для менеджера, который впервые берёт под управление незнакомую IT-команду.",
    "difficulty": "методология"
  },
  {
    "id": "105",
    "title": "Каково быть тимлидом и почему они так быстро выгорают",
    "link": "https://habr.com/ru/companies/productstar/articles/804883/",
    "source": "habr",
    "company": "productstar",
    "themes": [
      "leadership",
      "career"
    ],
    "section": "leadership",
    "summary": "Статья раскрывает роль тимлида, её особенности и причины профессионального выгорания на этой позиции.",
    "difficulty": "базовый"
  },
  {
    "id": "106",
    "title": "Настольная инструкция лида",
    "link": "https://habr.com/ru/companies/ozontech/articles/834804/",
    "source": "habr",
    "company": "Ozon",
    "themes": [
      "leadership",
      "processes"
    ],
    "section": "leadership",
    "summary": "Практическое руководство для лида по управлению командой и процессами в контексте A/B-тестирования на Ozon.",
    "difficulty": "методология"
  },
  {
    "id": "107",
    "title": "У тимлида есть только путь — как и зачем расти выше",
    "link": "https://habr.com/ru/companies/sbermarket/articles/805405/",
    "source": "habr",
    "company": "Kuper",
    "themes": [
      "career",
      "leadership"
    ],
    "section": "leadership",
    "summary": "Статья объясняет, зачем тимлиду расти выше своей роли и какой путь карьерного развития для этого существует.",
    "difficulty": "методология"
  },
  {
    "id": "108",
    "title": "Философия Continuous Coordination",
    "link": "https://t.me/thefutureofwork/1755",
    "source": "telegram",
    "company": "independent",
    "themes": [
      "processes",
      "team"
    ],
    "section": "leadership",
    "summary": "Философия непрерывной координации: принципы и подходы к организации согласованной работы команд и процессов.",
    "difficulty": "методология"
  },
  {
    "id": "109",
    "title": "Что подразумевает роль аналитика данных",
    "link": "https://gopractice.ru/skills/data_analysts_levels",
    "source": "gopractice",
    "company": "independent",
    "themes": [
      "career",
      "analytics-core"
    ],
    "section": "leadership",
    "summary": "Обзор обязанностей и навыков аналитика данных, помогающий читателю понять, что входит в эту роль.",
    "difficulty": "базовый"
  },
  {
    "id": "110",
    "title": "Я стал тимлидом и боюсь. Что почитать и зачем",
    "link": "https://habr.com/ru/companies/kaspersky/articles/821491/",
    "source": "habr",
    "company": "kaspersky",
    "themes": [
      "leadership",
      "career"
    ],
    "section": "leadership",
    "summary": "Подборка книг и ресурсов для новоиспечённых тимлидов, помогающая справиться с тревогой и войти в роль руководителя.",
    "difficulty": "базовый"
  },
  {
    "id": "111",
    "title": "AB тестирование: CUPED vs Stratification",
    "link": "https://habr.com/ru/companies/X5Tech/articles/826488/",
    "source": "habr",
    "company": "X5",
    "themes": [
      "experiments",
      "variance-reduction"
    ],
    "section": "analytics",
    "author": "Nazarov",
    "summary": "Сравнение методов снижения дисперсии CUPED и стратификации в AB-тестировании для повышения чувствительности экспериментов.",
    "difficulty": "продвинутый"
  },
  {
    "id": "112",
    "title": "AB тестирование: множественная проверка гипотез",
    "link": "https://habr.com/ru/companies/X5Tech/articles/842426/",
    "source": "habr",
    "company": "X5",
    "themes": [
      "experiments",
      "multiple-testing"
    ],
    "section": "analytics",
    "author": "Nazarov",
    "summary": "Разбор проблемы множественной проверки гипотез в A/B тестировании и методов контроля ошибок первого рода.",
    "difficulty": "продвинутый"
  },
  {
    "id": "113",
    "title": "Мифы о байесовском AB тестировании",
    "link": "https://habr.com/ru/companies/X5Tech/articles/900032/",
    "source": "habr",
    "company": "X5",
    "themes": [
      "experiments",
      "statistics"
    ],
    "section": "analytics",
    "author": "Nazarov",
    "summary": "Разбор распространённых заблуждений о байесовском подходе к AB-тестированию и как их избежать на практике.",
    "difficulty": "продвинутый"
  },
  {
    "id": "114",
    "title": "Проблема подглядывания и последовательное AB тестирование",
    "link": "https://habr.com/ru/companies/X5Tech/articles/926546/",
    "source": "habr",
    "company": "X5",
    "themes": [
      "experiments",
      "statistics"
    ],
    "section": "analytics",
    "author": "Nazarov",
    "summary": "Разбор проблемы множественных сравнений при непрерывном мониторинге AB-теста и методы последовательного тестирования для корректных выводов.",
    "difficulty": "продвинутый"
  },
  {
    "id": "115",
    "title": "Проксируй это: как ускорить AB-тесты и не попасть в ловушку метрик",
    "link": "https://habr.com/ru/companies/X5Tech/articles/974372/",
    "source": "habr",
    "company": "X5",
    "themes": [
      "experiments",
      "metrics"
    ],
    "section": "analytics",
    "author": "Erohin",
    "summary": "Методы использования прокси-метрик для ускорения AB-тестов и предотвращения ошибок при выборе показателей.",
    "difficulty": "продвинутый"
  },
  {
    "id": "116",
    "title": "Как мы научились честно считать эффект промокодов: Causal Inference в онлайн-доставке X5 Digital",
    "link": "https://habr.com/ru/companies/X5Tech/articles/1005410/",
    "source": "habr",
    "company": "X5",
    "themes": [
      "experiments",
      "causality"
    ],
    "section": "analytics",
    "author": "Korenkov",
    "summary": "Статья объясняет применение Causal Inference для корректного измерения эффекта промокодов в онлайн-доставке X5, решая проблему смещённых оценок.",
    "difficulty": "продвинутый"
  },
  {
    "id": "117",
    "title": "10 мифов об AB-тестировании: как избежать заблуждений",
    "link": "https://habr.com/ru/companies/yandex/articles/919966/",
    "source": "habr",
    "company": "Яндекс Go",
    "themes": [
      "experiments",
      "anti-patterns"
    ],
    "section": "analytics",
    "author": "Khakimova",
    "summary": "Разбирает 10 частых заблуждений об A/B-тестировании и помогает избежать типичных ошибок при проведении экспериментов.",
    "difficulty": "методология"
  },
  {
    "id": "118",
    "title": "Как мы запускали AB-тестирование в М2: опыт внедрения open source-платформы",
    "link": "https://habr.com/ru/companies/m2tech/articles/930724/",
    "source": "habr",
    "company": "М2",
    "themes": [
      "experiments",
      "platforms"
    ],
    "section": "analytics",
    "author": "Pankratova",
    "summary": "Практический опыт внедрения open source-платформы AB-тестирования в М2: как запустить эксперименты с нуля.",
    "difficulty": "методология"
  },
  {
    "id": "119",
    "title": "Офлайн AB тесты в ресторанах фастфуда. Часть 1",
    "link": "https://habr.com/ru/articles/902778/",
    "source": "habr",
    "company": "independent",
    "themes": [
      "experiments",
      "offline"
    ],
    "section": "analytics",
    "author": "Malaya",
    "summary": "Введение в проведение офлайн AB-тестов в ресторанах быстрого питания: методология и особенности экспериментов вне цифровой среды.",
    "difficulty": "методология"
  },
  {
    "id": "120",
    "title": "AB тесты и подглядывание: введение в последовательное тестирование",
    "link": "https://habr.com/ru/articles/988816/",
    "source": "habr",
    "company": "independent",
    "themes": [
      "experiments",
      "statistics"
    ],
    "section": "analytics",
    "author": "Petrov",
    "summary": "Введение в последовательное тестирование для AB-экспериментов: как избежать ошибок при подглядывании за результатами до окончания теста.",
    "difficulty": "методология"
  },
  {
    "id": "121",
    "title": "Методичка по AB-тестированию от аналитиков Авито. Часть 1",
    "link": "https://habr.com/ru/companies/avito/articles/936804/",
    "source": "habr",
    "company": "Avito",
    "themes": [
      "experiments",
      "statistics"
    ],
    "section": "analytics",
    "author": "Lunin",
    "summary": "Практическое руководство по AB-тестированию от аналитиков Авито: основы методологии и процессы проведения экспериментов.",
    "difficulty": "методология"
  },
  {
    "id": "122",
    "title": "Валидация каузальных моделей",
    "link": "https://habr.com/ru/companies/kuper/articles/990726/",
    "source": "habr",
    "company": "Kuper",
    "themes": [
      "experiments",
      "causality"
    ],
    "section": "analytics",
    "author": "Mosin",
    "summary": "Методы и подходы к проверке каузальных моделей для обеспечения достоверности причинно-следственных выводов в экспериментах.",
    "difficulty": "экспертный"
  },
  {
    "id": "123",
    "title": "У нас было 10k метрик, 500 AB-экспериментов и 500kk p-value каждый день",
    "link": "https://habr.com/ru/companies/avito/articles/947358/",
    "source": "habr",
    "company": "Avito",
    "themes": [
      "experiments",
      "platforms"
    ],
    "section": "analytics",
    "author": "Lenkov",
    "summary": "Статья описывает масштабную систему AB-тестирования Avito с обработкой миллионов p-value и решает задачу управления множественными сравнениями.",
    "difficulty": "продвинутый"
  },
  {
    "id": "124",
    "title": "Расширенный CUPAC для снижения дисперсии в AB экспериментах",
    "link": "https://habr.com/ru/articles/869998/",
    "source": "habr",
    "company": "independent",
    "themes": [
      "experiments",
      "variance-reduction"
    ],
    "section": "analytics",
    "author": "Ponomarev",
    "summary": "Расширение CUPAC: добавление внутриэкспериментальных ковариат к предэкспериментальным для дополнительного снижения дисперсии в AB-тестах.",
    "difficulty": "экспертный"
  }
]
