{
  "snapshot_date": "2026-02-23",
  "n_total": 5702,
  "price": {
    "p25": 13500,
    "median": 41900,
    "p75": 83000,
    "p90": 139990
  },
  "top_segments": [
    {
      "chip": "Intel",
      "size": 13,
      "count": 747,
      "median": 12000
    },
    {
      "chip": "M4",
      "size": 13,
      "count": 636,
      "median": 78890
    },
    {
      "chip": "M1",
      "size": 13,
      "count": 331,
      "median": 42000
    },
    {
      "chip": "M4",
      "size": 15,
      "count": 294,
      "median": 114845
    },
    {
      "chip": "Intel i5",
      "size": 13,
      "count": 251,
      "median": 20000
    },
    {
      "chip": "M5",
      "size": 14,
      "count": 244,
      "median": 147495
    },
    {
      "chip": "M2",
      "size": 13,
      "count": 210,
      "median": 55945
    },
    {
      "chip": "Intel",
      "size": 15,
      "count": 153,
      "median": 17000
    },
    {
      "chip": "Intel i7",
      "size": 15,
      "count": 97,
      "median": 26499
    },
    {
      "chip": "M1 Pro",
      "size": 16,
      "count": 87,
      "median": 77000
    }
  ],
  "median_by_chip": [
    {
      "chip": "Intel",
      "count": 1232,
      "median": 12000
    },
    {
      "chip": "M4",
      "count": 1054,
      "median": 93000
    },
    {
      "chip": "M1",
      "count": 518,
      "median": 41990
    },
    {
      "chip": "M2",
      "count": 346,
      "median": 57790
    },
    {
      "chip": "Intel i5",
      "count": 303,
      "median": 19000
    },
    {
      "chip": "M5",
      "count": 256,
      "median": 147495
    },
    {
      "chip": "Intel i7",
      "count": 215,
      "median": 30000
    },
    {
      "chip": "M3",
      "count": 189,
      "median": 73900
    },
    {
      "chip": "M4 Pro",
      "count": 156,
      "median": 185000
    },
    {
      "chip": "M1 Pro",
      "count": 131,
      "median": 76990
    }
  ],
  "m4_summary": {
    "count": 1296,
    "median": 99990,
    "p25": 77518,
    "p75": 143115
  },
  "coverage": {
    "total_queries": 33,
    "target_reached": 15,
    "empty_pages": 0,
    "soft_block": 0,
    "total_unique": 5702
  }
}